flexpy/AffixSelector.py
flexpy/Corpus.py
flexpy/FlexPyUtil.py
flexpy/FormGrouping.py
flexpy/LexEntry.py
flexpy/Lexicon.py
flexpy/PunctuationForm.py
flexpy/Rt.py
flexpy/Segment.py
flexpy/TagDict.py
flexpy/Text.py
flexpy/TextParagraph.py
flexpy/WordDistance.py
flexpy/WordForm.py
flexpy/XMLTagMap.py
flexpy/__init__.py
flexpy/tags/AStr.py
flexpy/tags/AUni.py
flexpy/tags/Abbreviation.py
flexpy/tags/AffixCategories.py
flexpy/tags/AffixSlots.py
flexpy/tags/AffixTemplates.py
flexpy/tags/Alias.py
flexpy/tags/AllowsComment.py
flexpy/tags/AllowsFeatureStructure.py
flexpy/tags/AllowsInstanceOf.py
flexpy/tags/AlternateForms.py
flexpy/tags/Analyses.py
flexpy/tags/AnalysisWss.py
flexpy/tags/AnalyzingAgents.py
flexpy/tags/AnnotationDefs.py
flexpy/tags/AnnotationType.py
flexpy/tags/Annotations.py
flexpy/tags/AnthroList.py
flexpy/tags/App.py
flexpy/tags/Approves.py
flexpy/tags/BackColor.py
flexpy/tags/BasedOn.py
flexpy/tags/BasicIPASymbol.py
flexpy/tags/BeginAnalysisIndex.py
flexpy/tags/BeginObject.py
flexpy/tags/BeginOffset.py
flexpy/tags/BeginRef.py
flexpy/tags/BeginSegment.py
flexpy/tags/BeginTimeOffset.py
flexpy/tags/BookAbbrev.py
flexpy/tags/BookAnnotations.py
flexpy/tags/BookName.py
flexpy/tags/BookNameAlt.py
flexpy/tags/Books.py
flexpy/tags/BoundaryMarkers.py
flexpy/tags/Bridge.py
flexpy/tags/CVPattern.py
flexpy/tags/CanCreateOrphan.py
flexpy/tags/CatalogSourceId.py
flexpy/tags/Category.py
flexpy/tags/Cells.py
flexpy/tags/ChapterVerseSepr.py
flexpy/tags/ChartMarkers.py
flexpy/tags/Charts.py
flexpy/tags/Checksum.py
flexpy/tags/CitationForm.py
flexpy/tags/ClassId.py
flexpy/tags/ClauseType.py
flexpy/tags/Codes.py
flexpy/tags/Column.py
flexpy/tags/ColumnInfo.py
flexpy/tags/Comment.py
flexpy/tags/CompDetails.py
flexpy/tags/ComplexEntryTypes.py
flexpy/tags/ComponentLexemes.py
flexpy/tags/CompoundRules.py
flexpy/tags/ConfidenceLevels.py
flexpy/tags/ConstChartTempl.py
flexpy/tags/Content.py
flexpy/tags/Contents.py
flexpy/tags/Context.py
flexpy/tags/ConvertCVDigitsOnExport.py
flexpy-0.0.7.dist-info/LICENSE
flexpy-0.0.7.dist-info/METADATA
flexpy-0.0.7.dist-info/WHEEL
flexpy-0.0.7.dist-info/top_level.txt
flexpy-0.0.7.dist-info/RECORD
