Metadata-Version: 2.1
Name: flexpy
Version: 0.0.7
Summary: Python API for SIL FieldWorks Language Explorer (FLEx)
Home-page: https://github.com/Kuhron/flexpy
Author: Wesley Kuhron Jones
Author-email: wesleykuhronjones@gmail.com
License: GPLv3
Platform: UNKNOWN
Classifier: License :: OSI Approved :: GNU General Public License (GPL)
Classifier: Programming Language :: Python :: 3
Classifier: Programming Language :: Python :: 3.8
